ghauto/__init__.py
ghauto/client.py
ghauto/slack_api.py
ghauto/api/__init__.py
ghauto/api/channels.py
ghauto/api/chat.py
ghauto/api/groups.py
ghauto/api/signup.py
ghauto/api/users.py
ghauto-0.1.0.dist-info/METADATA
ghauto-0.1.0.dist-info/WHEEL
ghauto-0.1.0.dist-info/top_level.txt
ghauto-0.1.0.dist-info/zip-safe
ghauto-0.1.0.dist-info/RECORD
