Metadata-Version: 2.1
Name: ghauto
Version: 0.1.0
Summary: Slack API wrapper
Home-page: UNKNOWN
Author: Slack Tester
Author-email: mrslackit@gmail.com
License: UNKNOWN
Platform: UNKNOWN
Classifier: Programming Language :: Python :: 3
Classifier: License :: OSI Approved :: MIT License
Classifier: Operating System :: OS Independent
Requires-Dist: requests (>=2.9.11)
Requires-Dist: typing (>=3.5.3.0)
Requires-Dist: responses (>=0.9.0)
